setup.cfg
setup.py
bgqmap/__init__.py
bgqmap/drmaa_wrapper.py
bgqmap/qmap.py
bgqmap/utils.py
bgqmap.egg-info/PKG-INFO
bgqmap.egg-info/SOURCES.txt
bgqmap.egg-info/dependency_links.txt
bgqmap.egg-info/entry_points.txt
bgqmap.egg-info/requires.txt
bgqmap.egg-info/top_level.txt