Metadata-Version: 1.1
Name: bgqmap
Version: 1.0.0
Summary: Bgqmap it's a python library and script to parallelize multiple jobs in a DRMAA compatible cluster.
Home-page: https://bitbucket.org/bgframework/bgqmap
Author: Jordi Deu-Pons
Author-email: jordi.deu@upf.edu
License: Apache License 2
Download-URL: https://bitbucket.org/bgframework/bgqmap/get/1.0.0.tar.gz
Platform: UNKNOWN
